judex/__init__.py
judex/core.py
judex/data.csv
judex/data.json
judex/database.py
judex/exceptions.py
judex/exporters.py
judex/extract.py
judex/items.py
judex/loaders.py
judex/middlewares.py
judex/models.py
judex/output_registry.py
judex/pydantic_pipeline.py
judex/settings.py
judex/types.py
judex/pipelines/__init__.py
judex/pipelines/csv_pipeline.py
judex/pipelines/database_pipeline.py
judex/pipelines/json_pipeline.py
judex/pipelines/jsonl_pipeline.py
judex/pipelines/metadata_pipeline.py
judex/spiders/__init__.py
judex/spiders/stf.py
judex/strategies/__init__.py
judex-1.2.0.dist-info/METADATA
judex-1.2.0.dist-info/WHEEL
judex-1.2.0.dist-info/entry_points.txt
judex-1.2.0.dist-info/licenses/LICENSE
judex-1.2.0.dist-info/RECORD
