Metadata-Version: 2.4
Name: judex
Version: 1.2.0
Summary: Judex Legal Case Scraper - Scrape legal cases from STF
Author-email: Gustavo Costa <gustavo@arcos.org.br>
License-File: LICENSE
Requires-Python: >=3.8
Requires-Dist: beautifulsoup4
Requires-Dist: pandas
Requires-Dist: pydantic
Requires-Dist: requests
Requires-Dist: scrapy
Requires-Dist: scrapy-selenium
Requires-Dist: selenium
Requires-Dist: sqlalchemy
Requires-Dist: typer
